blocksciencelabs/__init__.py
client/__init__.py
common/__init__.py
blocksciencelabs-0.1.21.dist-info/LICENSE
blocksciencelabs-0.1.21.dist-info/METADATA
blocksciencelabs-0.1.21.dist-info/WHEEL
blocksciencelabs-0.1.21.dist-info/top_level.txt
blocksciencelabs-0.1.21.dist-info/RECORD
