Metadata-Version: 2.1
Name: blocksciencelabs
Version: 0.1.21
Summary: BlockScience Labs Python SDK
Home-page: https://github.com/blockscience-labs/labs-sdk
Author: Tyler Mace
Author-email: tyler@blocksciencelabs.com
Project-URL: Bug Tracker, https://github.com/blockscience-labs/labs-sdk/issues
Classifier: Programming Language :: Python :: 3
Classifier: License :: OSI Approved :: MIT License
Classifier: Operating System :: OS Independent
Requires-Python: >=3.9
License-File: LICENSE
Requires-Dist: dill
